flycun_mcp_demo/__init__.py
flycun_mcp_demo-0.1.1.dist-info/METADATA
flycun_mcp_demo-0.1.1.dist-info/WHEEL
flycun_mcp_demo-0.1.1.dist-info/entry_points.txt
flycun_mcp_demo-0.1.1.dist-info/RECORD
