Metadata-Version: 2.4
Name: flycun-mcp-demo
Version: 0.1.1
Summary: Add your description here
Author-email: flycun <flycun@163.com>
Requires-Python: >=3.13
Requires-Dist: mcp[cli]>=1.9.3
